{"efVersion":"0.11.5","efModuleName":["CSS","Text","Transform"],"efExports":[{"TypeRef":["TextTransform",[]]},{"ValueRef":{"Ident":"capitalize"}},{"ValueRef":{"Ident":"lowercase"}},{"ValueRef":{"Ident":"textTransform"}},{"ValueRef":{"Ident":"uppercase"}},{"TypeInstanceRef":{"Ident":"eqTextTransform"}},{"TypeInstanceRef":{"Ident":"ordTextTransform"}},{"TypeInstanceRef":{"Ident":"genericTextTransform"}},{"TypeInstanceRef":{"Ident":"valTextTransform"}},{"TypeInstanceRef":{"Ident":"showTextTransform"}},{"TypeInstanceRef":{"Ident":"noneTextTransform"}},{"TypeInstanceRef":{"Ident":"initialTextTransform"}},{"TypeInstanceRef":{"Ident":"inheritTextTransform"}}],"efImports":[{"eiModule":["Prim"],"eiImportType":{"Implicit":[]},"eiImportedAs":null},{"eiModule":["CSS","Common"],"eiImportType":{"Explicit":[{"PositionedDeclarationRef":[{"start":[9,20],"name":"/Users/expede/Desktop/ro/bower_components/purescript-css/src/CSS/Text/Transform.purs","end":[9,33]},[],{"TypeClassRef":"Inherit"}]},{"PositionedDeclarationRef":[{"start":[9,35],"name":"/Users/expede/Desktop/ro/bower_components/purescript-css/src/CSS/Text/Transform.purs","end":[9,48]},[],{"TypeClassRef":"Initial"}]},{"PositionedDeclarationRef":[{"start":[9,50],"name":"/Users/expede/Desktop/ro/bower_components/purescript-css/src/CSS/Text/Transform.purs","end":[9,60]},[],{"TypeClassRef":"None"}]}]},"eiImportedAs":null},{"eiModule":["CSS","Property"],"eiImportType":{"Explicit":[{"PositionedDeclarationRef":[{"start":[10,22],"name":"/Users/expede/Desktop/ro/bower_components/purescript-css/src/CSS/Text/Transform.purs","end":[10,31]},[],{"TypeClassRef":"Val"}]}]},"eiImportedAs":null},{"eiModule":["CSS","String"],"eiImportType":{"Explicit":[{"PositionedDeclarationRef":[{"start":[11,20],"name":"/Users/expede/Desktop/ro/bower_components/purescript-css/src/CSS/Text/Transform.purs","end":[11,30]},[],{"ValueRef":{"Ident":"fromString"}}]}]},"eiImportedAs":null},{"eiModule":["CSS","Stylesheet"],"eiImportType":{"Explicit":[{"PositionedDeclarationRef":[{"start":[12,24],"name":"/Users/expede/Desktop/ro/bower_components/purescript-css/src/CSS/Text/Transform.purs","end":[12,27]},[],{"TypeRef":["CSS",[]]}]},{"PositionedDeclarationRef":[{"start":[12,29],"name":"/Users/expede/Desktop/ro/bower_components/purescript-css/src/CSS/Text/Transform.purs","end":[12,32]},[],{"ValueRef":{"Ident":"key"}}]}]},"eiImportedAs":null},{"eiModule":["Data","Eq"],"eiImportType":{"Explicit":[{"PositionedDeclarationRef":[{"start":[13,17],"name":"/Users/expede/Desktop/ro/bower_components/purescript-css/src/CSS/Text/Transform.purs","end":[13,25]},[],{"TypeClassRef":"Eq"}]}]},"eiImportedAs":null},{"eiModule":["Data","Function"],"eiImportType":{"Explicit":[{"PositionedDeclarationRef":[{"start":[14,23],"name":"/Users/expede/Desktop/ro/bower_components/purescript-css/src/CSS/Text/Transform.purs","end":[14,26]},[],{"ValueOpRef":"$"}]}]},"eiImportedAs":null},{"eiModule":["Data","Generic"],"eiImportType":{"Explicit":[{"PositionedDeclarationRef":[{"start":[15,22],"name":"/Users/expede/Desktop/ro/bower_components/purescript-css/src/CSS/Text/Transform.purs","end":[15,35]},[],{"TypeClassRef":"Generic"}]},{"PositionedDeclarationRef":[{"start":[15,37],"name":"/Users/expede/Desktop/ro/bower_components/purescript-css/src/CSS/Text/Transform.purs","end":[15,42]},[],{"ValueRef":{"Ident":"gShow"}}]}]},"eiImportedAs":null},{"eiModule":["Data","Ord"],"eiImportType":{"Explicit":[{"PositionedDeclarationRef":[{"start":[16,18],"name":"/Users/expede/Desktop/ro/bower_components/purescript-css/src/CSS/Text/Transform.purs","end":[16,27]},[],{"TypeClassRef":"Ord"}]}]},"eiImportedAs":null},{"eiModule":["Data","Show"],"eiImportType":{"Explicit":[{"PositionedDeclarationRef":[{"start":[17,19],"name":"/Users/expede/Desktop/ro/bower_components/purescript-css/src/CSS/Text/Transform.purs","end":[17,29]},[],{"TypeClassRef":"Show"}]}]},"eiImportedAs":null}],"efFixities":[],"efTypeFixities":[],"efDeclarations":[{"EDType":{"edTypeName":"TextTransform","edTypeKind":{"tag":"NamedKind","contents":[["Prim"],"Type"]},"edTypeDeclarationKind":{"DataType":{"args":[],"ctors":[["Uppercase",[]],["Lowercase",[]],["Capitalize",[]],["None",[]],["Initial",[]],["Inherit",[]]]}}}},{"EDValue":{"edValueName":{"Ident":"capitalize"},"edValueType":{"tag":"TypeConstructor","contents":[["CSS","Text","Transform"],"TextTransform"]}}},{"EDValue":{"edValueName":{"Ident":"lowercase"},"edValueType":{"tag":"TypeConstructor","contents":[["CSS","Text","Transform"],"TextTransform"]}}},{"EDValue":{"edValueName":{"Ident":"textTransform"},"edValueType":{"tag":"TypeApp","contents":[{"tag":"TypeApp","contents":[{"tag":"TypeConstructor","contents":[["Prim"],"Function"]},{"tag":"TypeConstructor","contents":[["CSS","Text","Transform"],"TextTransform"]}]},{"tag":"TypeApp","contents":[{"tag":"TypeConstructor","contents":[["CSS","Stylesheet"],"StyleM"]},{"tag":"TypeConstructor","contents":[["Data","Unit"],"Unit"]}]}]}}},{"EDValue":{"edValueName":{"Ident":"uppercase"},"edValueType":{"tag":"TypeConstructor","contents":[["CSS","Text","Transform"],"TextTransform"]}}},{"EDInstance":{"edInstanceClassName":[["Data","Eq"],"Eq"],"edInstanceName":{"Ident":"eqTextTransform"},"edInstanceTypes":[{"tag":"TypeConstructor","contents":[["CSS","Text","Transform"],"TextTransform"]}],"edInstanceConstraints":[]}},{"EDInstance":{"edInstanceClassName":[["Data","Ord"],"Ord"],"edInstanceName":{"Ident":"ordTextTransform"},"edInstanceTypes":[{"tag":"TypeConstructor","contents":[["CSS","Text","Transform"],"TextTransform"]}],"edInstanceConstraints":[]}},{"EDInstance":{"edInstanceClassName":[["Data","Generic"],"Generic"],"edInstanceName":{"Ident":"genericTextTransform"},"edInstanceTypes":[{"tag":"TypeConstructor","contents":[["CSS","Text","Transform"],"TextTransform"]}],"edInstanceConstraints":[]}},{"EDInstance":{"edInstanceClassName":[["CSS","Property"],"Val"],"edInstanceName":{"Ident":"valTextTransform"},"edInstanceTypes":[{"tag":"TypeConstructor","contents":[["CSS","Text","Transform"],"TextTransform"]}],"edInstanceConstraints":[]}},{"EDInstance":{"edInstanceClassName":[["Data","Show"],"Show"],"edInstanceName":{"Ident":"showTextTransform"},"edInstanceTypes":[{"tag":"TypeConstructor","contents":[["CSS","Text","Transform"],"TextTransform"]}],"edInstanceConstraints":[]}},{"EDInstance":{"edInstanceClassName":[["CSS","Common"],"None"],"edInstanceName":{"Ident":"noneTextTransform"},"edInstanceTypes":[{"tag":"TypeConstructor","contents":[["CSS","Text","Transform"],"TextTransform"]}],"edInstanceConstraints":[]}},{"EDInstance":{"edInstanceClassName":[["CSS","Common"],"Initial"],"edInstanceName":{"Ident":"initialTextTransform"},"edInstanceTypes":[{"tag":"TypeConstructor","contents":[["CSS","Text","Transform"],"TextTransform"]}],"edInstanceConstraints":[]}},{"EDInstance":{"edInstanceClassName":[["CSS","Common"],"Inherit"],"edInstanceName":{"Ident":"inheritTextTransform"},"edInstanceTypes":[{"tag":"TypeConstructor","contents":[["CSS","Text","Transform"],"TextTransform"]}],"edInstanceConstraints":[]}}],"efSourceSpan":{"start":[1,1],"name":"/Users/expede/Desktop/ro/bower_components/purescript-css/src/CSS/Text/Transform.purs","end":[61,14]}}